{
  "project_info": {
    "project_number": "902317945552",
    "project_id": "event-system-app-2026",
    "storage_bucket": "event-system-app-2026.firebasestorage.app"
  },
  "client": [
    {
      "client_info": {
        "mobilesdk_app_id": "1:902317945552:android:729e2f78972583dabb64d5",
        "android_client_info": {
          "package_name": "com.example.comp4206"
        }
      },
      "oauth_client": [],
      "api_key": [
        {
          "current_key": "AIzaSyDQKv7tOaoaCdPlXGlUsdKYo8gFQpEdWr4"
        }
      ],
      "services": {
        "appinvite_service": {
          "other_platform_oauth_client": []
        }
      }
    }
  ],
  "configuration_version": "1"
}